LICENSE
README.rst
setup.cfg
setup.py
src/mke_star_tracker_client/__init__.py
src/mke_star_tracker_client/star_tracker_client.py
src/mke_star_tracker_client.egg-info/PKG-INFO
src/mke_star_tracker_client.egg-info/SOURCES.txt
src/mke_star_tracker_client.egg-info/dependency_links.txt
src/mke_star_tracker_client.egg-info/top_level.txt